[
  {
    "id": "157ec4ba-429b-46a7-89b8-5f745f47af3d",
    "name": "liiista",
    "products": [
      {
        "name": "pane",
        "quantity": 1
      },
      {
        "name": "focaccia",
        "quantity": 1
      },
      {
        "name": "maiale",
        "quantity": 1
      },
      {
        "name": "cacca",
        "quantity": 1
      },
      {
        "name": "spacchio di mati",
        "quantity": 1
      },
      {
        "name": "lana",
        "quantity": 1
      }
    ],
    "budget": "45",
    "mode": "convenience",
    "userId": "12345",
    "createdAt": "2024-11-24T20:29:54.090Z",
    "updatedAt": "2024-11-24T20:29:54.090Z"
  },
  {
    "id": "d57202f8-8717-4125-9871-13981596bc34",
    "name": "nome lista ciao ciao",
    "products": [
      {
        "name": "cane",
        "quantity": 3
      }
    ],
    "budget": "200",
    "mode": "savings",
    "userId": "12345",
    "createdAt": "2024-11-24T20:52:57.522Z",
    "updatedAt": "2024-11-24T20:52:57.522Z"
  },
  {
    "id": "62a0986d-a6a4-43ab-9763-c4ca926530cb",
    "name": "lista 4",
    "products": [
      {
        "name": "cane",
        "quantity": 1
      }
    ],
    "budget": "23",
    "mode": "convenience",
    "userId": "12345",
    "createdAt": "2024-11-25T14:16:20.256Z",
    "updatedAt": "2024-11-25T14:16:20.256Z"
  },
  {
    "id": "e738a2fc-9c14-4637-b9f5-c34548140ba6",
    "name": "lista di melanzana",
    "products": [
      {
        "name": "cane",
        "quantity": 6
      }
    ],
    "budget": "45",
    "mode": "convenience",
    "userId": "12345",
    "createdAt": "2024-11-25T15:25:37.850Z",
    "updatedAt": "2024-11-25T15:25:37.850Z"
  },
  {
    "id": "d6b6aa81-e109-41dc-8ebc-801d9f8e22d6",
    "name": "prova",
    "products": [
      {
        "name": "melanzane sotto urina",
        "quantity": 3
      }
    ],
    "budget": "40",
    "mode": "savings",
    "userId": "12345",
    "createdAt": "2024-11-25T18:14:38.839Z",
    "updatedAt": "2024-11-25T18:14:38.839Z"
  }
]