[
  {
    "id": "71e3cd54-1c67-450d-a024-15cbb43ce6b5",
    "name": "mi",
    "products": [
      {
        "name": "j+",
        "quantity": 1
      },
      {
        "name": "miao",
        "quantity": 1
      }
    ],
    "budget": "0",
    "mode": "convenience",
    "userId": "12345",
    "createdAt": "2024-12-06T20:37:58.567Z",
    "updatedAt": "2024-12-06T20:37:58.567Z"
  },
  {
    "id": "5daec01a-257f-45ed-9999-7cfb3c3c89ce",
    "name": "Title",
    "products": [
      {
        "name": "a product",
        "quantity": 1
      },
      {
        "name": "another prod",
        "quantity": 1
      },
      {
        "name": "miao",
        "quantity": 1
      },
      {
        "name": "bau",
        "quantity": 1
      },
      {
        "name": "sau",
        "quantity": 1
      },
      {
        "name": "ron",
        "quantity": 1
      }
    ],
    "budget": "0",
    "mode": "convenience",
    "userId": "12345",
    "createdAt": "2024-12-07T17:11:00.553Z",
    "updatedAt": "2024-12-07T17:11:00.553Z"
  },
  {
    "id": "3d0bc87d-b1cc-47ab-a82c-95bf6ad17fe0",
    "name": "miao",
    "products": [
      {
        "name": "k",
        "quantity": 5
      }
    ],
    "budget": "0",
    "mode": "convenience",
    "userId": "12345",
    "createdAt": "2024-12-07T17:29:52.109Z",
    "updatedAt": "2024-12-07T17:29:52.109Z"
  },
  {
    "id": "c7e8d97e-f35d-4a37-a820-f9030c762ec9",
    "name": "Popop",
    "products": [
      {
        "name": "[pipfw",
        "quantity": 1
      },
      {
        "name": "miao",
        "quantity": 1
      },
      {
        "name": "miao",
        "quantity": 1
      },
      {
        "name": "pomodori",
        "quantity": 1
      }
    ],
    "budget": "0",
    "mode": "convenience",
    "userId": "12345",
    "createdAt": "2024-12-07T20:27:31.835Z",
    "updatedAt": "2024-12-07T20:27:31.835Z"
  },
  {
    "id": "6dcec4a4-7d54-48b6-b2a4-91c40c3ed774",
    "name": "z",
    "products": [
      {
        "name": "product",
        "quantity": 1
      },
      {
        "name": "Meow",
        "quantity": 1
      }
    ],
    "budget": "0",
    "mode": "convenience",
    "userId": "12345",
    "createdAt": "2024-12-07T20:58:42.887Z",
    "updatedAt": "2024-12-07T20:58:42.887Z"
  }
]